Workbook

Sheet Legend
A1: Role assignments — hitters
A3: WHAT TO EDIT — the yellow cells on the Assignments sheet:
A4: * One probability per role column. They should sum to 1.00 for each player; the 'Role Prob Sum' column checks this.
A5: * Role Start — when the player takes the job (see the Timing table on the Roles sheet).
A6: * Availability — YOURS to set: the share of the season you expect him healthy and on an MLB roster. 1.00 = full year.
A7: * Exp Apps / IP/App (pitchers) — how often he is handed the ball, and how long he stays. His innings are the two multiplied, so for a pitcher AVAILABILITY IS EXP APPS: it is not a multiplier on this sheet and Durability stays 1.00 for him.
A8: * Durability — the model's, from his own games-played record against others in the same role. Centred on 1.00 and allowed to go above it: a player who misses nothing beats the league-average missed time his role's anchor was built from. Overwrite it if you disagree; Proj PA multiplies both.
A9: * Pos / Bats (or Throws) — needed for the typed-slot allocation and the platoon splits.
A11: WHY PROBABILITIES AND NOT ONE ROLE:
A12: A player in a job battle is ~50% full-time / 30% platoon / 20% bench. Picking one label
A13: yields a plausible-looking PA figure that is the mean of a bimodal distribution — wrong in
A14: both worlds. Probabilities also give the model the variance, which is what season-long
... A48: cross-role ORDERING is more reliable than the absolute numbers.

Sheet Assignments
A1: PlayerId | B1: Name | C1: Team | D1: Age | E1: Bats | F1: Pos | G1: Last PA | H1: Career | I1: Suggested Role | J1: Role Start | K1: Role Share | L1: Availability | M1: Durability | N1: Full Time | O1: Everyday DH / 1B-DH | P1: Strong Side Platoon | Q1: Weak Side Platoon | R1: Catcher - Primary | S1: Catcher - Tandem | T1: Catcher - Backup | U1: Utility IF | V1: Utility OF / 4th OF | W1: Bench Bat | X1: Injury Replacement / 26th Man | Y1: Depth (no MLB PA) | Z1: Proj PA | AA1: Role Prob Sum | AB1: Proj vL Share | AC1: Notes
A2: ANCHORS -> | N2: 630 | O2: 600 | P2: 480 | Q2: 230 | R2: 500 | S2: 340 | T2: 180 | U2: 290 | V2: 300 | W2: 150 | X2: 90 | Y2: 1 | Z2: <- PA per 162 G at full availability
A3: anchor:vl_lhb | N3: 0.26 | O3: 0.26 | P3: 0.12 | Q3: 0.08 | R3: 0.26 | S3: 0.22 | T3: 0.24 | U3: 0.26 | V3: 0.24 | W3: 0.22 | X3: 0.26 | Y3: 0.26
A4: anchor:vl_rhb | N4: 0.29 | O4: 0.29 | P4: 0.45 | Q4: 0.68 | R4: 0.29 | S4: 0.38 | T4: 0.33 | U4: 0.31 | V4: 0.33 | W4: 0.36 | X4: 0.29 | Y4: 0.29
A5: 999999 | B5: EXAMPLE — delete this row | C5: FA | D5: 28 | E5: R | F5: 2B | I5: Full Time | J5: Early Season (~May) | K5: =IFERROR(INDEX(Roles!$B$17:$B$20,MATCH(J5,Roles!$A$17:$A$20,0)),1) | L5: 0.85 | M5: 0.92 | N5: 0.6 | P5: 0.3 | U5: 0.1 | Z5: =SUMPRODUCT(N5:Y5,$N$2:$Y$2)*$K5*$L5*$M5 | AA5: =SUM(N5:Y5) | AB5: =IFERROR(IF(UPPER($E5)="L",SUMPRODUCT(N5:Y5,$N$3:$Y$3,$N$2:$Y$2),SUMPRODUCT(N5:Y5,$N$4:$Y$4,$N$2:$Y$2))/(Z5/($K5*$L5*$M5)),"") | AC5: Unsigned; job battle. 60% full-time / 30% strong-side platoon / 10% utility. Missed April, and his own games-played record runs a little short of his role's.
A6: 592450 | B6: Aaron Judge | C6: NYY | D6: 35 | E6: R | F6: RF | G6: 285 | H6: 2822 | I6: Full Time | J6: Opening Day | K6: =IFERROR(INDEX(Roles!$B$17:$B$20,MATCH(J6,Roles!$A$17:$A$20,0)),1) | L6: 1 | M6: 0.9355526 | N6: 1 | Z6: =SUMPRODUCT(N6:Y6,$N$2:$Y$2)*$K6*$L6*$M6 | AA6: =SUM(N6:Y6) | AB6: =IFERROR(IF(UPPER($E6)="L",SUMPRODUCT(N6:Y6,$N$3:$Y$3,$N$2:$Y$2),SUMPRODUCT(N6:Y6,$N$4:$Y$4,$N$2:$Y$2))/(Z6/($K6*$L6*$M6)),"")
A7: 680664 | B7: Eduardo Valencia | C7: DET | D7: 27 | E7: R | F7: C | G7: 138 | H7: 138 | I7: Bench Bat | J7: Opening Day | K7: =IFERROR(INDEX(Roles!$B$17:$B$20,MATCH(J7,Roles!$A$17:$A$20,0)),1) | L7: 1 | M7: 1 | U7: 0.4 | W7: 0.6 | Z7: =SUMPRODUCT(N7:Y7,$N$2:$Y$2)*$K7*$L7*$M7 | AA7: =SUM(N7:Y7) | AB7: =IFERROR(IF(UPPER($E7)="L",SUMPRODUCT(N7:Y7,$N$3:$Y$3,$N$2:$Y$2),SUMPRODUCT(N7:Y7,$N$4:$Y$4,$N$2:$Y$2))/(Z7/($K7*$L7*$M7)),"")
A8: 691002 | B8: Yohandy Morales | C8: WSH | D8: 26 | E8: R | F8: 1B | G8: 47 | H8: 47 | I8: Weak Side Platoon | J8: Opening Day | K8: =IFERROR(INDEX(Roles!$B$17:$B$20,MATCH(J8,Roles!$A$17:$A$20,0)),1) | L8: 1 | M8: 1 | Q8: 0.6 | U8: 0.4 | Z8: =SUMPRODUCT(N8:Y8,$N$2:$Y$2)*$K8*$L8*$M8 | AA8: =SUM(N8:Y8) | AB8: =IFERROR(IF(UPPER($E8)="L",SUMPRODUCT(N8:Y8,$N$3:$Y$3,$N$2:$Y$2),SUMPRODUCT(N8:Y8,$N$4:$Y$4,$N$2:$Y$2))/(Z8/($K8*$L8*$M8)),"")
A9: 804668 | B9: Rafael Flores Jr. | C9: PIT | D9: 26 | E9: R | F9: C | G9: 163 | H9: 180 | I9: Catcher - Primary | J9: Opening Day | K9: =IFERROR(INDEX(Roles!$B$17:$B$20,MATCH(J9,Roles!$A$17:$A$20,0)),1) | L9: 1 | M9: 1 | R9: 0.75 | S9: 0.25 | Z9: =SUMPRODUCT(N9:Y9,$N$2:$Y$2)*$K9*$L9*$M9 | AA9: =SUM(N9:Y9) | AB9: =IFERROR(IF(UPPER($E9)="L",SUMPRODUCT(N9:Y9,$N$3:$Y$3,$N$2:$Y$2),SUMPRODUCT(N9:Y9,$N$4:$Y$4,$N$2:$Y$2))/(Z9/($K9*$L9*$M9)),"")
A10: 660271 | B10: Shohei Ohtani | C10: LAD | D10: 32 | E10: L | F10: P | G10: 618 | H10: 3341 | I10: Everyday DH / 1B-DH | J10: Opening Day | K10: =IFERROR(INDEX(Roles!$B$17:$B$20,MATCH(J10,Roles!$A$17:$A$20,0)),1) | L10: 1 | M10: 1.1150872 | O10: 1 | Z10: =SUMPRODUCT(N10:Y10,$N$2:$Y$2)*$K10*$L10*$M10 | AA10: =SUM(N10:Y10) | AB10: =IFERROR(IF(UPPER($E10)="L",SUMPRODUCT(N10:Y10,$N$3:$Y$3,$N$2:$Y$2),SUMPRODUCT(N10:Y10,$N$4:$Y$4,$N$2:$Y$2))/(Z10/($K10*$L10*$M10)),"")
A11: 663728 | B11: Cal Raleigh | C11: SEA | D11: 30 | E11: S | F11: C | G11: 530 | H11: 2847 | I11: Catcher - Primary | J11: Opening Day | K11: =IFERROR(INDEX(Roles!$B$17:$B$20,MATCH(J11,Roles!$A$17:$A$20,0)),1) | L11: 1 | M11: 1.15 | R11: 1 | Z11: =SUMPRODUCT(N11:Y11,$N$2:$Y$2)*$K11*$L11*$M11 | AA11: =SUM(N11:Y11) | AB11: =IFERROR(IF(UPPER($E11)="L",SUMPRODUCT(N11:Y11,$N$3:$Y$3,$N$2:$Y$2),SUMPRODUCT(N11:Y11,$N$4:$Y$4,$N$2:$Y$2))/(Z11/($K11*$L11*$M11)),"")
A12: 519317 | B12: Giancarlo Stanton | C12: NYY | D12: 37 | E12: R | F12: RF | G12: 96 | H12: 1703 | I12: Full Time | J12: Opening Day | K12: =IFERROR(INDEX(Roles!$B$17:$B$20,MATCH(J12,Roles!$A$17:$A$20,0)),1) | L12: 1 | M12: 0.64061847 | N12: 1 | Z12: =SUMPRODUCT(N12:Y12,$N$2:$Y$2)*$K12*$L12*$M12 | AA12: =SUM(N12:Y12) | AB12: =IFERROR(IF(UPPER($E12)="L",SUMPRODUCT(N12:Y12,$N$3:$Y$3,$N$2:$Y$2),SUMPRODUCT(N12:Y12,$N$4:$Y$4,$N$2:$Y$2))/(Z12/($K12*$L12*$M12)),"")
A13: 656941 | B13: Kyle Schwarber | C13: PHI | D13: 34 | E13: L | F13: 1B | G13: 701 | H13: 3506 | I13: Everyday DH / 1B-DH | J13: Opening Day | K13: =IFERROR(INDEX(Roles!$B$17:$B$20,MATCH(J13,Roles!$A$17:$A$20,0)),1) | L13: 1 | M13: 1.15 | O13: 1 | Z13: =SUMPRODUCT(N13:Y13,$N$2:$Y$2)*$K13*$L13*$M13 | AA13: =SUM(N13:Y13) | AB13: =IFERROR(IF(UPPER($E13)="L",SUMPRODUCT(N13:Y13,$N$3:$Y$3,$N$2:$Y$2),SUMPRODUCT(N13:Y13,$N$4:$Y$4,$N$2:$Y$2))/(Z13/($K13*$L13*$M13)),"")
A14: 608596 | B14: Tom Murphy | C14: SF | D14: 36 | E14: R | F14: C | G14: 38 | H14: 239 | I14: Depth (no MLB PA) | J14: Opening Day | K14: =IFERROR(INDEX(Roles!$B$17:$B$20,MATCH(J14,Roles!$A$17:$A$20,0)),1) | L14: 1 | M14: 1 | Y14: 1 | Z14: =SUMPRODUCT(N14:Y14,$N$2:$Y$2)*$K14*$L14*$M14 | AA14: =SUM(N14:Y14) | AB14: =IFERROR(IF(UPPER($E14)="L",SUMPRODUCT(N14:Y14,$N$3:$Y$3,$N$2:$Y$2),SUMPRODUCT(N14:Y14,$N$4:$Y$4,$N$2:$Y$2))/(Z14/($K14*$L14*$M14)),"")
A15: 680837 | B15: Ryan Fitzgerald | C15: MIN | D15: 33 | E15: L | F15: SS | G15: 53 | H15: 53 | I15: Bench Bat | J15: Opening Day | K15: =IFERROR(INDEX(Roles!$B$17:$B$20,MATCH(J15,Roles!$A$17:$A$20,0)),1) | L15: 1 | M15: 1 | W15: 1 | Z15: =SUMPRODUCT(N15:Y15,$N$2:$Y$2)*$K15*$L15*$M15 | AA15: =SUM(N15:Y15) | AB15: =IFERROR(IF(UPPER($E15)="L",SUMPRODUCT(N15:Y15,$N$3:$Y$3,$N$2:$Y$2),SUMPRODUCT(N15:Y15,$N$4:$Y$4,$N$2:$Y$2))/(Z15/($K15*$L15*$M15)),"")
A16: 665742 | B16: Juan Soto | C16: NYM | D16: 28 | E16: L | F16: LF | G16: 482 | H16: 3282 | I16: Full Time | J16: Opening Day | K16: =IFERROR(INDEX(Roles!$B$17:$B$20,MATCH(J16,Roles!$A$17:$A$20,0)),1) | L16: 1 | M16: 1.057946 | N16: 1 | Z16: =SUMPRODUCT(N16:Y16,$N$2:$Y$2)*$K16*$L16*$M16 | AA16: =SUM(N16:Y16) | AB16: =IFERROR(IF(UPPER($E16)="L",SUMPRODUCT(N16:Y16,$N$3:$Y$3,$N$2:$Y$2),SUMPRODUCT(N16:Y16,$N$4:$Y$4,$N$2:$Y$2))/(Z16/($K16*$L16*$M16)),"")
A17: 621439 | B17: Byron Buxton | C17: MIN | D17: 33 | E17: R | F17: CF | G17: 408 | H17: 2067 | I17: Full Time | J17: Opening Day | K17: =IFERROR(INDEX(Roles!$B$17:$B$20,MATCH(J17,Roles!$A$17:$A$20,0)),1) | L17: 1 | M17: 0.90835406 | N17: 1 | Z17: =SUMPRODUCT(N17:Y17,$N$2:$Y$2)*$K17*$L17*$M17 | AA17: =SUM(N17:Y17) | AB17: =IFERROR(IF(UPPER($E17)="L",SUMPRODUCT(N17:Y17,$N$3:$Y$3,$N$2:$Y$2),SUMPRODUCT(N17:Y17,$N$4:$Y$4,$N$2:$Y$2))/(Z17/($K17*$L17*$M17)),"")
A18: 808959 | B18: Munetaka Murakami | C18: CWS | D18: 27 | E18: L | F18: 1B | G18: 553 | H18: 553 | I18: Full Time | J18: Opening Day | K18: =IFERROR(INDEX(Roles!$B$17:$B$20,MATCH(J18,Roles!$A$17:$A$20,0)),1) | L18: 1 | M18: 0.97986885 | N18: 1 | Z18: =SUMPRODUCT(N18:Y18,$N$2:$Y$2)*$K18*$L18*$M18 | AA18: =SUM(N18:Y18) | AB18: =IFERROR(IF(UPPER($E18)="L",SUMPRODUCT(N18:Y18,$N$3:$Y$3,$N$2:$Y$2),SUMPRODUCT(N18:Y18,$N$4:$Y$4,$N$2:$Y$2))/(Z18/($K18*$L18*$M18)),"")
A19: 695491 | B19: Joshua Báez | C19: STL | D19: 24 | E19: R | F19: LF | G19: 108 | H19: 108 | I19: Bench Bat | J19: Opening Day | K19: =IFERROR(INDEX(Roles!$B$17:$B$20,MATCH(J19,Roles!$A$17:$A$20,0)),1) | L19: 1 | M19: 1 | W19: 0.85 | X19: 0.15 | Z19: =SUMPRODUCT(N19:Y19,$N$2:$Y$2)*$K19*$L19*$M19 | AA19: =SUM(N19:Y19) | AB19: =IFERROR(IF(UPPER($E19)="L",SUMPRODUCT(N19:Y19,$N$3:$Y$3,$N$2:$Y$2),SUMPRODUCT(N19:Y19,$N$4:$Y$4,$N$2:$Y$2))/(Z19/($K19*$L19*$M19)),"")
A20: 624413 | B20: Pete Alonso | C20: BAL | D20: 32 | E20: R | F20: 1B | G20: 700 | H20: 3447 | I20: Full Time | J20: Opening Day | K20: =IFERROR(INDEX(Roles!$B$17:$B$20,MATCH(J20,Roles!$A$17:$A$20,0)),1) | L20: 1 | M20: 1.15 | N20: 1 | Z20: =SUMPRODUCT(N20:Y20,$N$2:$Y$2)*$K20*$L20*$M20 | AA20: =SUM(N20:Y20) | AB20: =IFERROR(IF(UPPER($E20)="L",SUMPRODUCT(N20:Y20,$N$3:$Y$3,$N$2:$Y$2),SUMPRODUCT(N20:Y20,$N$4:$Y$4,$N$2:$Y$2))/(Z20/($K20*$L20*$M20)),"")
A21: 699013 | B21: Esmerlyn Valdez | C21: PIT | D21: 23 | E21: R | F21: RF | G21: 287 | H21: 287 | I21: Bench Bat | J21: Opening Day | K21: =IFERROR(INDEX(Roles!$B$17:$B$20,MATCH(J21,Roles!$A$17:$A$20,0)),1) | L21: 1 | M21: 1 | N21: 0.4 | W21: 0.6 | Z21: =SUMPRODUCT(N21:Y21,$N$2:$Y$2)*$K21*$L21*$M21 | AA21: =SUM(N21:Y21) | AB21: =IFERROR(IF(UPPER($E21)="L",SUMPRODUCT(N21:Y21,$N$3:$Y$3,$N$2:$Y$2),SUMPRODUCT(N21:Y21,$N$4:$Y$4,$N$2:$Y$2))/(Z21/($K21*$L21*$M21)),"")
A22: 621550 | B22: Patrick Wisdom | C22: SEA | D22: 35 | E22: R | F22: 3B | G22: 50 | H22: 1060 | I22: Weak Side Platoon | J22: Opening Day | K22: =IFERROR(INDEX(Roles!$B$17:$B$20,MATCH(J22,Roles!$A$17:$A$20,0)),1) | L22: 1 | M22: 1 | Q22: 1 | Z22: =SUMPRODUCT(N22:Y22,$N$2:$Y$2)*$K22*$L22*$M22 | AA22: =SUM(N22:Y22) | AB22: =IFERROR(IF(UPPER($E22)="L",SUMPRODUCT(N22:Y22,$N$3:$Y$3,$N$2:$Y$2),SUMPRODUCT(N22:Y22,$N$4:$Y$4,$N$2:$Y$2))/(Z22/($K22*$L22*$M22)),"")
A23: 666703 | B23: Eguy Rosario | C23: SD | D23: 27 | E23: R | F23: 3B | G23: 57 | H23: 100 | I23: Depth (no MLB PA) | J23: Opening Day | K23: =IFERROR(INDEX(Roles!$B$17:$B$20,MATCH(J23,Roles!$A$17:$A$20,0)),1) | L23: 1 | M23: 1 | Y23: 1 | Z23: =SUMPRODUCT(N23:Y23,$N$2:$Y$2)*$K23*$L23*$M23 | AA23: =SUM(N23:Y23) | AB23: =IFERROR(IF(UPPER($E23)="L",SUMPRODUCT(N23:Y23,$N$3:$Y$3,$N$2:$Y$2),SUMPRODUCT(N23:Y23,$N$4:$Y$4,$N$2:$Y$2))/(Z23/($K23*$L23*$M23)),"")
A24: 828599 | B24: Lucas Spence | C24: HOU | D24: 24 | E24: L | F24: CF | G24: 63 | H24: 63 | I24: Full Time | J24: Opening Day | K24: =IFERROR(INDEX(Roles!$B$17:$B$20,MATCH(J24,Roles!$A$17:$A$20,0)),1) | L24: 1 | M24: 1 | N24: 0.6 | V24: 0.4 | Z24: =SUMPRODUCT(N24:Y24,$N$2:$Y$2)*$K24*$L24*$M24 | AA24: =SUM(N24:Y24) | AB24: =IFERROR(IF(UPPER($E24)="L",SUMPRODUCT(N24:Y24,$N$3:$Y$3,$N$2:$Y$2),SUMPRODUCT(N24:Y24,$N$4:$Y$4,$N$2:$Y$2))/(Z24/($K24*$L24*$M24)),"")
A25: 608369 | B25: Corey Seager | C25: TEX | D25: 33 | E25: L | F25: SS | G25: 436 | H25: 2613 | I25: Full Time | J25: Opening Day | K25: =IFERROR(INDEX(Roles!$B$17:$B$20,MATCH(J25,Roles!$A$17:$A$20,0)),1) | L25: 1 | M25: 0.91090392 | N25: 1 | Z25: =SUMPRODUCT(N25:Y25,$N$2:$Y$2)*$K25*$L25*$M25 | AA25: =SUM(N25:Y25) | AB25: =IFERROR(IF(UPPER($E25)="L",SUMPRODUCT(N25:Y25,$N$3:$Y$3,$N$2:$Y$2),SUMPRODUCT(N25:Y25,$N$4:$Y$4,$N$2:$Y$2))/(Z25/($K25*$L25*$M25)),"")
A26: 691406 | B26: Junior Caminero | C26: TB | D26: 23 | E26: R | F26: 3B | G26: 702 | H26: 1568 | I26: Full Time | J26: Opening Day | K26: =IFERROR(INDEX(Roles!$B$17:$B$20,MATCH(J26,Roles!$A$17:$A$20,0)),1) | L26: 1 | M26: 1.0885444 | N26: 1 | Z26: =SUMPRODUCT(N26:Y26,$N$2:$Y$2)*$K26*$L26*$M26 | AA26: =SUM(N26:Y26) | AB26: =IFERROR(IF(UPPER($E26)="L",SUMPRODUCT(N26:Y26,$N$3:$Y$3,$N$2:$Y$2),SUMPRODUCT(N26:Y26,$N$4:$Y$4,$N$2:$Y$2))/(Z26/($K26*$L26*$M26)),"")
A27: 670541 | B27: Yordan Alvarez | C27: HOU | D27: 30 | E27: L | F27: LF | G27: 692 | H27: 2583 | I27: Everyday DH / 1B-DH | J27: Opening Day | K27: =IFERROR(INDEX(Roles!$B$17:$B$20,MATCH(J27,Roles!$A$17:$A$20,0)),1) | L27: 1 | M27: 0.98063845 | O27: 1 | Z27: =SUMPRODUCT(N27:Y27,$N$2:$Y$2)*$K27*$L27*$M27 | AA27: =SUM(N27:Y27) | AB27: =IFERROR(IF(UPPER($E27)="L",SUMPRODUCT(N27:Y27,$N$3:$Y$3,$N$2:$Y$2),SUMPRODUCT(N27:Y27,$N$4:$Y$4,$N$2:$Y$2))/(Z27/($K27*$L27*$M27)),"")
A28: 696100 | B28: Hunter Goodman | C28: COL | D28: 27 | E28: R | F28: C | G28: 574 | H28: 1454 | I28: Catcher - Primary | J28: Opening Day | K28: =IFERROR(INDEX(Roles!$B$17:$B$20,MATCH(J28,Roles!$A$17:$A$20,0)),1) | L28: 1 | M28: 1.0993046 | R28: 1 | Z28: =SUMPRODUCT(N28:Y28,$N$2:$Y$2)*$K28*$L28*$M28 | AA28: =SUM(N28:Y28) | AB28: =IFERROR(IF(UPPER($E28)="L",SUMPRODUCT(N28:Y28,$N$3:$Y$3,$N$2:$Y$2),SUMPRODUCT(N28:Y28,$N$4:$Y$4,$N$2:$Y$2))/(Z28/($K28*$L28*$M28)),"")
A29: 681481 | B29: Kerry Carpenter | C29: DET | D29: 29 | E29: L | F29: RF | G29: 259 | H29: 1591 | I29: Bench Bat | J29: Opening Day | K29: =IFERROR(INDEX(Roles!$B$17:$B$20,MATCH(J29,Roles!$A$17:$A$20,0)),1) | L29: 1 | M29: 1.0328381 | W29: 0.85 | X29: 0.15 | Z29: =SUMPRODUCT(N29:Y29,$N$2:$Y$2)*$K29*$L29*$M29 | AA29: =SUM(N29:Y29) | AB29: =IFERROR(IF(UPPER($E29)="L",SUMPRODUCT(N29:Y29,$N$3:$Y$3,$N$2:$Y$2),SUMPRODUCT(N29:Y29,$N$4:$Y$4,$N$2:$Y$2))/(Z29/($K29*$L29*$M29)),"")
A30: 695657 | B30: Colson Montgomery | C30: CWS | D30: 25 | E30: L | F30: SS | G30: 638 | H30: 922 | I30: Full Time | J30: Opening Day | K30: =IFERROR(INDEX(Roles!$B$17:$B$20,MATCH(J30,Roles!$A$17:$A$20,0)),1) | L30: 1 | M30: 1.0047621 | N30: 1 | Z30: =SUMPRODUCT(N30:Y30,$N$2:$Y$2)*$K30*$L30*$M30 | AA30: =SUM(N30:Y30) | AB30: =IFERROR(IF(UPPER($E30)="L",SUMPRODUCT(N30:Y30,$N$3:$Y$3,$N$2:$Y$2),SUMPRODUCT(N30:Y30,$N$4:$Y$4,$N$2:$Y$2))/(Z30/($K30*$L30*$M30)),"")
A31: 700250 | B31: Ben Rice | C31: NYY | D31: 28 | E31: L | F31: 1B | G31: 667 | H31: 1375 | I31: Everyday DH / 1B-DH | J31: Opening Day | K31: =IFERROR(INDEX(Roles!$B$17:$B$20,MATCH(J31,Roles!$A$17:$A$20,0)),1) | L31: 1 | M31: 1.0254547 | O31: 1 | Z31: =SUMPRODUCT(N31:Y31,$N$2:$Y$2)*$K31*$L31*$M31 | AA31: =SUM(N31:Y31) | AB31: =IFERROR(IF(UPPER($E31)="L",SUMPRODUCT(N31:Y31,$N$3:$Y$3,$N$2:$Y$2),SUMPRODUCT(N31:Y31,$N$4:$Y$4,$N$2:$Y$2))/(Z31/($K31*$L31*$M31)),"")
A32: 678577 | B32: Junior Perez | C32: CWS | D32: 25 | E32: R | F32: LF | G32: 36 | H32: 36 | I32: Injury Replacement / 26th Man | J32: Opening Day | K32: =IFERROR(INDEX(Roles!$B$17:$B$20,MATCH(J32,Roles!$A$17:$A$20,0)),1) | L32: 1 | M32: 1 | X32: 1 | Z32: =SUMPRODUCT(N32:Y32,$N$2:$Y$2)*$K32*$L32*$M32 | AA32: =SUM(N32:Y32) | AB32: =IFERROR(IF(UPPER($E32)="L",SUMPRODUCT(N32:Y32,$N$3:$Y$3,$N$2:$Y$2),SUMPRODUCT(N32:Y32,$N$4:$Y$4,$N$2:$Y$2))/(Z32/($K32*$L32*$M32)),"")
A33: 805904 | B33: Zach Cole | C33: HOU | D33: 26 | E33: L | F33: LF | G33: 53 | H33: 105 | I33: Bench Bat | J33: Opening Day | K33: =IFERROR(INDEX(Roles!$B$17:$B$20,MATCH(J33,Roles!$A$17:$A$20,0)),1) | L33: 1 | M33: 1 | W33: 1 | Z33: =SUMPRODUCT(N33:Y33,$N$2:$Y$2)*$K33*$L33*$M33 | AA33: =SUM(N33:Y33) | AB33: =IFERROR(IF(UPPER($E33)="L",SUMPRODUCT(N33:Y33,$N$3:$Y$3,$N$2:$Y$2),SUMPRODUCT(N33:Y33,$N$4:$Y$4,$N$2:$Y$2))/(Z33/($K33*$L33*$M33)),"")
A34: 553993 | B34: Eugenio Suárez | C34: CIN | D34: 35 | E34: R | F34: 3B | G34: 498 | H34: 3118 | I34: Everyday DH / 1B-DH | J34: Opening Day | K34: =IFERROR(INDEX(Roles!$B$17:$B$20,MATCH(J34,Roles!$A$17:$A$20,0)),1) | L34: 1 | M34: 1.0939475 | O34: 1 | Z34: =SUMPRODUCT(N34:Y34,$N$2:$Y$2)*$K34*$L34*$M34 | AA34: =SUM(N34:Y34) | AB34: =IFERROR(IF(UPPER($E34)="L",SUMPRODUCT(N34:Y34,$N$3:$Y$3,$N$2:$Y$2),SUMPRODUCT(N34:Y34,$N$4:$Y$4,$N$2:$Y$2))/(Z34/($K34*$L34*$M34)),"")
A35: 691718 | B35: Pete Crow-Armstrong | C35: CHC | D35: 25 | E35: L | F35: CF | G35: 726 | H35: 1802 | I35: Full Time | J35: Opening Day | K35: =IFERROR(INDEX(Roles!$B$17:$B$20,MATCH(J35,Roles!$A$17:$A$20,0)),1) | L35: 1 | M35: 1.15 | N35: 1 | Z35: =SUMPRODUCT(N35:Y35,$N$2:$Y$2)*$K35*$L35*$M35 | AA35: =SUM(N35:Y35) | AB35: =IFERROR(IF(UPPER($E35)="L",SUMPRODUCT(N35:Y35,$N$3:$Y$3,$N$2:$Y$2),SUMPRODUCT(N35:Y35,$N$4:$Y$4,$N$2:$Y$2))/(Z35/($K35*$L35*$M35)),"")
A36: 624414 | B36: Christian Arroyo | C36: BOS | D36: 32 | E36: R | F36: 2B | G36: 206 | H36: 506 | I36: Depth (no MLB PA) | J36: Opening Day | K36: =IFERROR(INDEX(Roles!$B$17:$B$20,MATCH(J36,Roles!$A$17:$A$20,0)),1) | L36: 1 | M36: 1 | Y36: 1 | Z36: =SUMPRODUCT(N36:Y36,$N$2:$Y$2)*$K36*$L36*$M36 | AA36: =SUM(N36:Y36) | AB36: =IFERROR(IF(UPPER($E36)="L",SUMPRODUCT(N36:Y36,$N$3:$Y$3,$N$2:$Y$2),SUMPRODUCT(N36:Y36,$N$4:$Y$4,$N$2:$Y$2))/(Z36/($K36*$L36*$M36)),"")
A37: 621311 | B37: David Dahl | C37: PHI | D37: 33 | E37: L | F37: LF | G37: 62 | H37: 71 | I37: Depth (no MLB PA) | J37: Opening Day | K37: =IFERROR(INDEX(Roles!$B$17:$B$20,MATCH(J37,Roles!$A$17:$A$20,0)),1) | L37: 1 | M37: 1 | Y37: 1 | Z37: =SUMPRODUCT(N37:Y37,$N$2:$Y$2)*$K37*$L37*$M37 | AA37: =SUM(N37:Y37) | AB37: =IFERROR(IF(UPPER($E37)="L",SUMPRODUCT(N37:Y37,$N$3:$Y$3,$N$2:$Y$2),SUMPRODUCT(N37:Y37,$N$4:$Y$4,$N$2:$Y$2))/(Z37/($K37*$L37*$M37)),"")
A38: 669398 | B38: Gage Workman | C38: SD | D38: 27 | E38: L | F38: 3B | G38: 41 | H38: 58 | I38: Bench Bat | J38: Opening Day | K38: =IFERROR(INDEX(Roles!$B$17:$B$20,MATCH(J38,Roles!$A$17:$A$20,0)),1) | L38: 1 | M38: 1 | W38: 1 | Z38: =SUMPRODUCT(N38:Y38,$N$2:$Y$2)*$K38*$L38*$M38 | AA38: =SUM(N38:Y38) | AB38: =IFERROR(IF(UPPER($E38)="L",SUMPRODUCT(N38:Y38,$N$3:$Y$3,$N$2:$Y$2),SUMPRODUCT(N38:Y38,$N$4:$Y$4,$N$2:$Y$2))/(Z38/($K38*$L38*$M38)),"")
A39: 672960 | B39: Kazuma Okamoto | C39: TOR | D39: 31 | E39: R | F39: 3B | G39: 636 | H39: 636 | I39: Full Time | J39: Opening Day | K39: =IFERROR(INDEX(Roles!$B$17:$B$20,MATCH(J39,Roles!$A$17:$A$20,0)),1) | L39: 1 | M39: 1.0790302 | N39: 1 | Z39: =SUMPRODUCT(N39:Y39,$N$2:$Y$2)*$K39*$L39*$M39 | AA39: =SUM(N39:Y39) | AB39: =IFERROR(IF(UPPER($E39)="L",SUMPRODUCT(N39:Y39,$N$3:$Y$3,$N$2:$Y$2),SUMPRODUCT(N39:Y39,$N$4:$Y$4,$N$2:$Y$2))/(Z39/($K39*$L39*$M39)),"")
A40: 672359 | B40: Tirso Ornelas | C40: SD | D40: 27 | E40: L | F40: LF | G40: 16 | H40: 16 | I40: Depth (no MLB PA) | J40: Opening Day | K40: =IFERROR(INDEX(Roles!$B$17:$B$20,MATCH(J40,Roles!$A$17:$A$20,0)),1) | L40: 1 | M40: 1 | Y40: 1 | Z40: =SUMPRODUCT(N40:Y40,$N$2:$Y$2)*$K40*$L40*$M40 | AA40: =SUM(N40:Y40) | AB40: =IFERROR(IF(UPPER($E40)="L",SUMPRODUCT(N40:Y40,$N$3:$Y$3,$N$2:$Y$2),SUMPRODUCT(N40:Y40,$N$4:$Y$4,$N$2:$Y$2))/(Z40/($K40*$L40*$M40)),"")
A41: 701762 | B41: Nick Kurtz | C41: OAK | D41: 24 | E41: L | F41: 1B | G41: 434 | H41: 923 | I41: Full Time | J41: Opening Day | K41: =IFERROR(INDEX(Roles!$B$17:$B$20,MATCH(J41,Roles!$A$17:$A$20,0)),1) | L41: 1 | M41: 0.91551691 | N41: 1 | Z41: =SUMPRODUCT(N41:Y41,$N$2:$Y$2)*$K41*$L41*$M41 | AA41: =SUM(N41:Y41) | AB41: =IFERROR(IF(UPPER($E41)="L",SUMPRODUCT(N41:Y41,$N$3:$Y$3,$N$2:$Y$2),SUMPRODUCT(N41:Y41,$N$4:$Y$4,$N$2:$Y$2))/(Z41/($K41*$L41*$M41)),"")
A42: 683090 | B42: Matthew Lugo | C42: LAA | D42: 26 | E42: R | F42: LF | G42: 15 | H42: 85 | I42: Utility OF / 4th OF | J42: Opening Day | K42: =IFERROR(INDEX(Roles!$B$17:$B$20,MATCH(J42,Roles!$A$17:$A$20,0)),1) | L42: 1 | M42: 1 | V42: 0.7 | W42: 0.3 | Z42: =SUMPRODUCT(N42:Y42,$N$2:$Y$2)*$K42*$L42*$M42 | AA42: =SUM(N42:Y42) | AB42: =IFERROR(IF(UPPER($E42)="L",SUMPRODUCT(N42:Y42,$N$3:$Y$3,$N$2:$Y$2),SUMPRODUCT(N42:Y42,$N$4:$Y$4,$N$2:$Y$2))/(Z42/($K42*$L42*$M42)),"")
A43: 669899 | B43: Ryan Ward | C43: LAD | D43: 29 | E43: L | F43: LF | G43: 60 | H43: 60 | I43: Bench Bat | J43: Opening Day | K43: =IFERROR(INDEX(Roles!$B$17:$B$20,MATCH(J43,Roles!$A$17:$A$20,0)),1) | L43: 1 | M43: 1 | W43: 1 | Z43: =SUMPRODUCT(N43:Y43,$N$2:$Y$2)*$K43*$L43*$M43 | AA43: =SUM(N43:Y43) | AB43: =IFERROR(IF(UPPER($E43)="L",SUMPRODUCT(N43:Y43,$N$3:$Y$3,$N$2:$Y$2),SUMPRODUCT(N43:Y43,$N$4:$Y$4,$N$2:$Y$2))/(Z43/($K43*$L43*$M43)),"")
A44: 665155 | B44: Nick Maton | C44: CWS | D44: 30 | E44: L | F44: 1B | G44: 63 | H44: 446 | I44: Bench Bat | J44: Opening Day | K44: =IFERROR(INDEX(Roles!$B$17:$B$20,MATCH(J44,Roles!$A$17:$A$20,0)),1) | L44: 1 | M44: 1 | W44: 1 | Z44: =SUMPRODUCT(N44:Y44,$N$2:$Y$2)*$K44*$L44*$M44 | AA44: =SUM(N44:Y44) | AB44: =IFERROR(IF(UPPER($E44)="L",SUMPRODUCT(N44:Y44,$N$3:$Y$3,$N$2:$Y$2),SUMPRODUCT(N44:Y44,$N$4:$Y$4,$N$2:$Y$2))/(Z44/($K44*$L44*$M44)),"")
A45: 646240 | B45: Rafael Devers | C45: SF | D45: 30 | E45: L | F45: 1B | G45: 633 | H45: 3233 | I45: Full Time | J45: Opening Day | K45: =IFERROR(INDEX(Roles!$B$17:$B$20,MATCH(J45,Roles!$A$17:$A$20,0)),1) | L45: 1 | M45: 1.1454913 | N45: 1 | Z45: =SUMPRODUCT(N45:Y45,$N$2:$Y$2)*$K45*$L45*$M45 | AA45: =SUM(N45:Y45) | AB45: =IFERROR(IF(UPPER($E45)="L",SUMPRODUCT(N45:Y45,$N$3:$Y$3,$N$2:$Y$2),SUMPRODUCT(N45:Y45,$N$4:$Y$4,$N$2:$Y$2))/(Z45/($K45*$L45*$M45)),"")
A46: 660670 | B46: Ronald Acuña Jr. | C46: ATL | D46: 29 | E46: R | F46: RF | G46: 469 | H46: 2371 | I46: Full Time | J46: Opening Day | K46: =IFERROR(INDEX(Roles!$B$17:$B$20,MATCH(J46,Roles!$A$17:$A$20,0)),1) | L46: 1 | M46: 0.85055717 | N46: 1 | Z46: =SUMPRODUCT(N46:Y46,$N$2:$Y$2)*$K46*$L46*$M46 | AA46: =SUM(N46:Y46) | AB46: =IFERROR(IF(UPPER($E46)="L",SUMPRODUCT(N46:Y46,$N$3:$Y$3,$N$2:$Y$2),SUMPRODUCT(N46:Y46,$N$4:$Y$4,$N$2:$Y$2))/(Z46/($K46*$L46*$M46)),"")
A47: 670223 | B47: Matt Mervis | C47: MIA | D47: 29 | E47: L | F47: 1B | G47: 134 | H47: 261 | I47: Bench Bat | J47: Opening Day | K47: =IFERROR(INDEX(Roles!$B$17:$B$20,MATCH(J47,Roles!$A$17:$A$20,0)),1) | L47: 1 | M47: 1 | W47: 1 | Z47: =SUMPRODUCT(N47:Y47,$N$2:$Y$2)*$K47*$L47*$M47 | AA47: =SUM(N47:Y47) | AB47: =IFERROR(IF(UPPER($E47)="L",SUMPRODUCT(N47:Y47,$N$3:$Y$3,$N$2:$Y$2),SUMPRODUCT(N47:Y47,$N$4:$Y$4,$N$2:$Y$2))/(Z47/($K47*$L47*$M47)),"")
A48: 688760 | B48: Blaine Crim | C48: COL | D48: 30 | E48: R | F48: 1B | G48: 74 | H48: 74 | I48: Bench Bat | J48: Opening Day | K48: =IFERROR(INDEX(Roles!$B$17:$B$20,MATCH(J48,Roles!$A$17:$A$20,0)),1) | L48: 1 | M48: 1 | W48: 1 | Z48: =SUMPRODUCT(N48:Y48,$N$2:$Y$2)*$K48*$L48*$M48 | AA48: =SUM(N48:Y48) | AB48: =IFERROR(IF(UPPER($E48)="L",SUMPRODUCT(N48:Y48,$N$3:$Y$3,$N$2:$Y$2),SUMPRODUCT(N48:Y48,$N$4:$Y$4,$N$2:$Y$2))/(Z48/($K48*$L48*$M48)),"")
A49: 641933 | B49: Tyler O'Neill | C49: BAL | D49: 32 | E49: R | F49: RF | G49: 260 | H49: 1591 | I49: Injury Replacement / 26th Man | J49: Opening Day | K49: =IFERROR(INDEX(Roles!$B$17:$B$20,MATCH(J49,Roles!$A$17:$A$20,0)),1) | L49: 1 | M49: 0.98223287 | X49: 1 | Z49: =SUMPRODUCT(N49:Y49,$N$2:$Y$2)*$K49*$L49*$M49 | AA49: =SUM(N49:Y49) | AB49: =IFERROR(IF(UPPER($E49)="L",SUMPRODUCT(N49:Y49,$N$3:$Y$3,$N$2:$Y$2),SUMPRODUCT(N49:Y49,$N$4:$Y$4,$N$2:$Y$2))/(Z49/($K49*$L49*$M49)),"")
A50: 666197 | B50: Grae Kessinger | C50: HOU | D50: 29 | E50: R | F50: 3B | G50: 25 | H50: 70 | I50: Depth (no MLB PA) | J50: Opening Day | K50: =IFERROR(INDEX(Roles!$B$17:$B$20,MATCH(J50,Roles!$A$17:$A$20,0)),1) | L50: 1 | M50: 1 | Y50: 1 | Z50: =SUMPRODUCT(N50:Y50,$N$2:$Y$2)*$K50*$L50*$M50 | AA50: =SUM(N50:Y50) | AB50: =IFERROR(IF(UPPER($E50)="L",SUMPRODUCT(N50:Y50,$N$3:$Y$3,$N$2:$Y$2),SUMPRODUCT(N50:Y50,$N$4:$Y$4,$N$2:$Y$2))/(Z50/($K50*$L50*$M50)),"")
A51: 667670 | B51: Brent Rooker | C51: OAK | D51: 32 | E51: R | F51: RF | G51: 203 | H51: 2078 | I51: Full Time | J51: Opening Day | K51: =IFERROR(INDEX(Roles!$B$17:$B$20,MATCH(J51,Roles!$A$17:$A$20,0)),1) | L51: 1 | M51: 0.89135497 | N51: 1 | Z51: =SUMPRODUCT(N51:Y51,$N$2:$Y$2)*$K51*$L51*$M51 | AA51: =SUM(N51:Y51) | AB51: =IFERROR(IF(UPPER($E51)="L",SUMPRODUCT(N51:Y51,$N$3:$Y$3,$N$2:$Y$2),SUMPRODUCT(N51:Y51,$N$4:$Y$4,$N$2:$Y$2))/(Z51/($K51*$L51*$M51)),"")
A52: 682985 | B52: Riley Greene | C52: DET | D52: 26 | E52: L | F52: LF | G52: 592 | H52: 2665 | I52: Full Time | J52: Opening Day | K52: =IFERROR(INDEX(Roles!$B$17:$B$20,MATCH(J52,Roles!$A$17:$A$20,0)),1) | L52: 1 | M52: 1.1344419 | N52: 1 | Z52: =SUMPRODUCT(N52:Y52,$N$2:$Y$2)*$K52*$L52*$M52 | AA52: =SUM(N52:Y52) | AB52: =IFERROR(IF(UPPER($E52)="L",SUMPRODUCT(N52:Y52,$N$3:$Y$3,$N$2:$Y$2),SUMPRODUCT(N52:Y52,$N$4:$Y$4,$N$2:$Y$2))/(Z52/($K52*$L52*$M52)),"")
A53: 671284 | B53: Tim Elko | C53: CWS | D53: 28 | E53: R | F53: 1B | G53: 72 | H53: 72 | I53: Bench Bat | J53: Opening Day | K53: =IFERROR(INDEX(Roles!$B$17:$B$20,MATCH(J53,Roles!$A$17:$A$20,0)),1) | L53: 1 | M53: 1 | W53: 1 | Z53: =SUMPRODUCT(N53:Y53,$N$2:$Y$2)*$K53*$L53*$M53 | AA53: =SUM(N53:Y53) | AB53: =IFERROR(IF(UPPER($E53)="L",SUMPRODUCT(N53:Y53,$N$3:$Y$3,$N$2:$Y$2),SUMPRODUCT(N53:Y53,$N$4:$Y$4,$N$2:$Y$2))/(Z53/($K53*$L53*$M53)),"")
A54: 571970 | B54: Max Muncy | C54: LAD | D54: 36 | E54: L | F54: 3B | G54: 561 | H54: 2386 | I54: Full Time | J54: Opening Day | K54: =IFERROR(INDEX(Roles!$B$17:$B$20,MATCH(J54,Roles!$A$17:$A$20,0)),1) | L54: 1 | M54: 0.9763504 | N54: 0.7 | P54: 0.3 | Z54: =SUMPRODUCT(N54:Y54,$N$2:$Y$2)*$K54*$L54*$M54 | AA54: =SUM(N54:Y54) | AB54: =IFERROR(IF(UPPER($E54)="L",SUMPRODUCT(N54:Y54,$N$3:$Y$3,$N$2:$Y$2),SUMPRODUCT(N54:Y54,$N$4:$Y$4,$N$2:$Y$2))/(Z54/($K54*$L54*$M54)),"")
A55: 664040 | B55: Brandon Lowe | C55: PIT | D55: 32 | E55: L | F55: 2B | G55: 656 | H55: 2336 | I55: Full Time | J55: Opening Day | K55: =IFERROR(INDEX(Roles!$B$17:$B$20,MATCH(J55,Roles!$A$17:$A$20,0)),1) | L55: 1 | M55: 1.0732452 | N55: 1 | Z55: =SUMPRODUCT(N55:Y55,$N$2:$Y$2)*$K55*$L55*$M55 | AA55: =SUM(N55:Y55) | AB55: =IFERROR(IF(UPPER($E55)="L",SUMPRODUCT(N55:Y55,$N$3:$Y$3,$N$2:$Y$2),SUMPRODUCT(N55:Y55,$N$4:$Y$4,$N$2:$Y$2))/(Z55/($K55*$L55*$M55)),"")
A56: 676369 | B56: Nelson Velázquez | C56: HOU | D56: 28 | E56: R | F56: LF | G56: 113 | H56: 728 | I56: Bench Bat | J56: Opening Day | K56: =IFERROR(INDEX(Roles!$B$17:$B$20,MATCH(J56,Roles!$A$17:$A$20,0)),1) | L56: 1 | M56: 1 | W56: 0.85 | X56: 0.15 | Z56: =SUMPRODUCT(N56:Y56,$N$2:$Y$2)*$K56*$L56*$M56 | AA56: =SUM(N56:Y56) | AB56: =IFERROR(IF(UPPER($E56)="L",SUMPRODUCT(N56:Y56,$N$3:$Y$3,$N$2:$Y$2),SUMPRODUCT(N56:Y56,$N$4:$Y$4,$N$2:$Y$2))/(Z56/($K56*$L56*$M56)),"")
A57: 693409 | B57: César Prieto | C57: STL | D57: 28 | E57: L | F57: 3B | G57: 39 | H57: 45 | I57: Bench Bat | J57: Opening Day | K57: =IFERROR(INDEX(Roles!$B$17:$B$20,MATCH(J57,Roles!$A$17:$A$20,0)),1) | L57: 1 | M57: 1 | W57: 0.85 | X57: 0.15 | Z57: =SUMPRODUCT(N57:Y57,$N$2:$Y$2)*$K57*$L57*$M57 | AA57: =SUM(N57:Y57) | AB57: =IFERROR(IF(UPPER($E57)="L",SUMPRODUCT(N57:Y57,$N$3:$Y$3,$N$2:$Y$2),SUMPRODUCT(N57:Y57,$N$4:$Y$4,$N$2:$Y$2))/(Z57/($K57*$L57*$M57)),"")
A58: 686482 | B58: Logan Driscoll | C58: TB | D58: 29 | E58: L | F58: C | G58: 37 | H58: 37 | I58: Depth (no MLB PA) | J58: Opening Day | K58: =IFERROR(INDEX(Roles!$B$17:$B$20,MATCH(J58,Roles!$A$17:$A$20,0)),1) | L58: 1 | M58: 1 | Y58: 1 | Z58: =SUMPRODUCT(N58:Y58,$N$2:$Y$2)*$K58*$L58*$M58 | AA58: =SUM(N58:Y58) | AB58: =IFERROR(IF(UPPER($E58)="L",SUMPRODUCT(N58:Y58,$N$3:$Y$3,$N$2:$Y$2),SUMPRODUCT(N58:Y58,$N$4:$Y$4,$N$2:$Y$2))/(Z58/($K58*$L58*$M58)),"")
A59: 545350 | B59: Jake Marisnick | C59: LAD | D59: 36 | E59: R | F59: CF | G59: 83 | H59: 165 | I59: Depth (no MLB PA) | J59: Opening Day | K59: =IFERROR(INDEX(Roles!$B$17:$B$20,MATCH(J59,Roles!$A$17:$A$20,0)),1) | L59: 1 | M59: 1 | Y59: 1 | Z59: =SUMPRODUCT(N59:Y59,$N$2:$Y$2)*$K59*$L59*$M59 | AA59: =SUM(N59:Y59) | AB59: =IFERROR(IF(UPPER($E59)="L",SUMPRODUCT(N59:Y59,$N$3:$Y$3,$N$2:$Y$2),SUMPRODUCT(N59:Y59,$N$4:$Y$4,$N$2:$Y$2))/(Z59/($K59*$L59*$M59)),"")
A60: 594807 | B60: Adam Duvall | C60: ATL | D60: 38 | E60: R | F60: RF | G60: 330 | H60: 998 | I60: Depth (no MLB PA) | J60: Opening Day | K60: =IFERROR(INDEX(Roles!$B$17:$B$20,MATCH(J60,Roles!$A$17:$A$20,0)),1) | L60: 1 | M60: 1 | Y60: 1 | Z60: =SUMPRODUCT(N60:Y60,$N$2:$Y$2)*$K60*$L60*$M60 | AA60: =SUM(N60:Y60) | AB60: =IFERROR(IF(UPPER($E60)="L",SUMPRODUCT(N60:Y60,$N$3:$Y$3,$N$2:$Y$2),SUMPRODUCT(N60:Y60,$N$4:$Y$4,$N$2:$Y$2))/(Z60/($K60*$L60*$M60)),"")
A61: 641598 | B61: Mitch Garver | C61: SEA | D61: 36 | E61: R | F61: C | G61: 149 | H61: 1428 | I61: Catcher - Tandem | J61: Opening Day | K61: =IFERROR(INDEX(Roles!$B$17:$B$20,MATCH(J61,Roles!$A$17:$A$20,0)),1) | L61: 1 | M61: 1 | S61: 1 | Z61: =SUMPRODUCT(N61:Y61,$N$2:$Y$2)*$K61*$L61*$M61 | AA61: =SUM(N61:Y61) | AB61: =IFERROR(IF(UPPER($E61)="L",SUMPRODUCT(N61:Y61,$N$3:$Y$3,$N$2:$Y$2),SUMPRODUCT(N61:Y61,$N$4:$Y$4,$N$2:$Y$2))/(Z61/($K61*$L61*$M61)),"")
A62: 664901 | B62: Danny Mendick | C62: CWS | D62: 33 | E62: R | F62: 3B | G62: 141 | H62: 316 | I62: Depth (no MLB PA) | J62: Opening Day | K62: =IFERROR(INDEX(Roles!$B$17:$B$20,MATCH(J62,Roles!$A$17:$A$20,0)),1) | L62: 1 | M62: 1 | Y62: 1 | Z62: =SUMPRODUCT(N62:Y62,$N$2:$Y$2)*$K62*$L62*$M62 | AA62: =SUM(N62:Y62) | AB62: =IFERROR(IF(UPPER($E62)="L",SUMPRODUCT(N62:Y62,$N$3:$Y$3,$N$2:$Y$2),SUMPRODUCT(N62:Y62,$N$4:$Y$4,$N$2:$Y$2))/(Z62/($K62*$L62*$M62)),"")
A63: 660710 | B63: Rodolfo Durán | C63: SD | D63: 29 | E63: R | F63: C | G63: 91 | H63: 91 | I63: Injury Replacement / 26th Man | J63: Opening Day | K63: =IFERROR(INDEX(Roles!$B$17:$B$20,MATCH(J63,Roles!$A$17:$A$20,0)),1) | L63: 1 | M63: 1 | X63: 1 | Z63: =SUMPRODUCT(N63:Y63,$N$2:$Y$2)*$K63*$L63*$M63 | AA63: =SUM(N63:Y63) | AB63: =IFERROR(IF(UPPER($E63)="L",SUMPRODUCT(N63:Y63,$N$3:$Y$3,$N$2:$Y$2),SUMPRODUCT(N63:Y63,$N$4:$Y$4,$N$2:$Y$2))/(Z63/($K63*$L63*$M63)),"")
A64: 666176 | B64: Jo Adell | C64: CLE | D64: 28 | E64: R | F64: RF | G64: 660 | H64: 2031 | I64: Everyday DH / 1B-DH | J64: Opening Day | K64: =IFERROR(INDEX(Roles!$B$17:$B$20,MATCH(J64,Roles!$A$17:$A$20,0)),1) | L64: 1 | M64: 1.15 | O64: 1 | Z64: =SUMPRODUCT(N64:Y64,$N$2:$Y$2)*$K64*$L64*$M64 | AA64: =SUM(N64:Y64) | AB64: =IFERROR(IF(UPPER($E64)="L",SUMPRODUCT(N64:Y64,$N$3:$Y$3,$N$2:$Y$2),SUMPRODUCT(N64:Y64,$N$4:$Y$4,$N$2:$Y$2))/(Z64/($K64*$L64*$M64)),"")
A65: 621566 | B65: Matt Olson | C65: ATL | D65: 33 | E65: L | F65: 1B | G65: 698 | H65: 3526 | I65: Full Time | J65: Opening Day | K65: =IFERROR(INDEX(Roles!$B$17:$B$20,MATCH(J65,Roles!$A$17:$A$20,0)),1) | L65: 1 | M65: 1.15 | N65: 1 | Z65: =SUMPRODUCT(N65:Y65,$N$2:$Y$2)*$K65*$L65*$M65 | AA65: =SUM(N65:Y65) | AB65: =IFERROR(IF(UPPER($E65)="L",SUMPRODUCT(N65:Y65,$N$3:$Y$3,$N$2:$Y$2),SUMPRODUCT(N65:Y65,$N$4:$Y$4,$N$2:$Y$2))/(Z65/($K65*$L65*$M65)),"")
A66: 695020 | B66: Tanner Murray | C66: CWS | D66: 27 | E66: R | F66: LF | G66: 33 | H66: 33 | I66: Utility IF | J66: Opening Day | K66: =IFERROR(INDEX(Roles!$B$17:$B$20,MATCH(J66,Roles!$A$17:$A$20,0)),1) | L66: 1 | M66: 1 | U66: 0.7 | W66: 0.3 | Z66: =SUMPRODUCT(N66:Y66,$N$2:$Y$2)*$K66*$L66*$M66 | AA66: =SUM(N66:Y66) | AB66: =IFERROR(IF(UPPER($E66)="L",SUMPRODUCT(N66:Y66,$N$3:$Y$3,$N$2:$Y$2),SUMPRODUCT(N66:Y66,$N$4:$Y$4,$N$2:$Y$2))/(Z66/($K66*$L66*$M66)),"")
A67: 687263 | B67: Zach Neto | C67: LAA | D67: 26 | E67: R | F67: SS | G67: 704 | H67: 2189 | I67: Full Time | J67: Opening Day | K67: =IFERROR(INDEX(Roles!$B$17:$B$20,MATCH(J67,Roles!$A$17:$A$20,0)),1) | L67: 1 | M67: 1.1174428 | N67: 1 | Z67: =SUMPRODUCT(N67:Y67,$N$2:$Y$2)*$K67*$L67*$M67 | AA67: =SUM(N67:Y67) | AB67: =IFERROR(IF(UPPER($E67)="L",SUMPRODUCT(N67:Y67,$N$3:$Y$3,$N$2:$Y$2),SUMPRODUCT(N67:Y67,$N$4:$Y$4,$N$2:$Y$2))/(Z67/($K67*$L67*$M67)),"")
A68: 608360 | B68: Chris Okey | C68: LAA | D68: 32 | E68: R | F68: C | G68: 2 | H68: 15 | I68: Depth (no MLB PA) | J68: Opening Day | K68: =IFERROR(INDEX(Roles!$B$17:$B$20,MATCH(J68,Roles!$A$17:$A$20,0)),1) | L68: 1 | M68: 1 | Y68: 1 | Z68: =SUMPRODUCT(N68:Y68,$N$2:$Y$2)*$K68*$L68*$M68 | AA68: =SUM(N68:Y68) | AB68: =IFERROR(IF(UPPER($E68)="L",SUMPRODUCT(N68:Y68,$N$3:$Y$3,$N$2:$Y$2),SUMPRODUCT(N68:Y68,$N$4:$Y$4,$N$2:$Y$2))/(Z68/($K68*$L68*$M68)),"")
A69: 663330 | B69: Jahmai Jones | C69: BOS | D69: 29 | E69: R | F69: LF | G69: 181 | H69: 389 | I69: Weak Side Platoon | J69: Opening Day | K69: =IFERROR(INDEX(Roles!$B$17:$B$20,MATCH(J69,Roles!$A$17:$A$20,0)),1) | L69: 1 | M69: 1 | Q69: 0.6 | W69: 0.4 | Z69: =SUMPRODUCT(N69:Y69,$N$2:$Y$2)*$K69*$L69*$M69 | AA69: =SUM(N69:Y69) | AB69: =IFERROR(IF(UPPER($E69)="L",SUMPRODUCT(N69:Y69,$N$3:$Y$3,$N$2:$Y$2),SUMPRODUCT(N69:Y69,$N$4:$Y$4,$N$2:$Y$2))/(Z69/($K69*$L69*$M69)),"")
A70: 669221 | B70: Sean Murphy | C70: ATL | D70: 32 | E70: R | F70: C | G70: 121 | H70: 1772 | I70: Strong Side Platoon | J70: Opening Day | K70: =IFERROR(INDEX(Roles!$B$17:$B$20,MATCH(J70,Roles!$A$17:$A$20,0)),1) | L70: 1 | M70: 1 | P70: 0.6 | R70: 0.4 | Z70: =SUMPRODUCT(N70:Y70,$N$2:$Y$2)*$K70*$L70*$M70 | AA70: =SUM(N70:Y70) | AB70: =IFERROR(IF(UPPER($E70)="L",SUMPRODUCT(N70:Y70,$N$3:$Y$3,$N$2:$Y$2),SUMPRODUCT(N70:Y70,$N$4:$Y$4,$N$2:$Y$2))/(Z70/($K70*$L70*$M70)),"")
A71: 691723 | B71: Coby Mayo | C71: BAL | D71: 25 | E71: R | F71: 3B | G71: 454 | H71: 794 | I71: Everyday DH / 1B-DH | J71: Opening Day | K71: =IFERROR(INDEX(Roles!$B$17:$B$20,MATCH(J71,Roles!$A$17:$A$20,0)),1) | L71: 1 | M71: 0.86056469 | O71: 0.85 | W71: 0.15 | Z71: =SUMPRODUCT(N71:Y71,$N$2:$Y$2)*$K71*$L71*$M71 | AA71: =SUM(N71:Y71) | AB71: =IFERROR(IF(UPPER($E71)="L",SUMPRODUCT(N71:Y71,$N$3:$Y$3,$N$2:$Y$2),SUMPRODUCT(N71:Y71,$N$4:$Y$4,$N$2:$Y$2))/(Z71/($K71*$L71*$M71)),"")
A72: 670242 | B72: Matt Wallner | C72: MIN | D72: 29 | E72: L | F72: RF | G72: 135 | H72: 1107 | I72: Full Time | J72: Opening Day | K72: =IFERROR(INDEX(Roles!$B$17:$B$20,MATCH(J72,Roles!$A$17:$A$20,0)),1) | L72: 1 | M72: 0.68991582 | N72: 1 | Z72: =SUMPRODUCT(N72:Y72,$N$2:$Y$2)*$K72*$L72*$M72 | AA72: =SUM(N72:Y72) | AB72: =IFERROR(IF(UPPER($E72)="L",SUMPRODUCT(N72:Y72,$N$3:$Y$3,$N$2:$Y$2),SUMPRODUCT(N72:Y72,$N$4:$Y$4,$N$2:$Y$2))/(Z72/($K72*$L72*$M72)),"")
A73: 679529 | B73: Spencer Torkelson | C73: DET | D73: 27 | E73: R | F73: 1B | G73: 612 | H73: 2730 | I73: Full Time | J73: Opening Day | K73: =IFERROR(INDEX(Roles!$B$17:$B$20,MATCH(J73,Roles!$A$17:$A$20,0)),1) | L73: 1 | M73: 1.1174428 | N73: 1 | Z73: =SUMPRODUCT(N73:Y73,$N$2:$Y$2)*$K73*$L73*$M73 | AA73: =SUM(N73:Y73) | AB73: =IFERROR(IF(UPPER($E73)="L",SUMPRODUCT(N73:Y73,$N$3:$Y$3,$N$2:$Y$2),SUMPRODUCT(N73:Y73,$N$4:$Y$4,$N$2:$Y$2))/(Z73/($K73*$L73*$M73)),"")
A74: 545361 | B74: Mike Trout | C74: LAA | D74: 35 | E74: R | F74: CF | G74: 634 | H74: 2177 | I74: Everyday DH / 1B-DH | J74: Opening Day | K74: =IFERROR(INDEX(Roles!$B$17:$B$20,MATCH(J74,Roles!$A$17:$A$20,0)),1) | L74: 1 | M74: 0.97471932 | O74: 1 | Z74: =SUMPRODUCT(N74:Y74,$N$2:$Y$2)*$K74*$L74*$M74 | AA74: =SUM(N74:Y74) | AB74: =IFERROR(IF(UPPER($E74)="L",SUMPRODUCT(N74:Y74,$N$3:$Y$3,$N$2:$Y$2),SUMPRODUCT(N74:Y74,$N$4:$Y$4,$N$2:$Y$2))/(Z74/($K74*$L74*$M74)),"")
A75: 575929 | B75: Willson Contreras | C75: BOS | D75: 35 | E75: R | F75: 1B | G75: 535 | H75: 2438 | I75: Full Time | J75: Opening Day | K75: =IFERROR(INDEX(Roles!$B$17:$B$20,MATCH(J75,Roles!$A$17:$A$20,0)),1) | L75: 1 | M75: 1.0077987 | N75: 1 | Z75: =SUMPRODUCT(N75:Y75,$N$2:$Y$2)*$K75*$L75*$M75 | AA75: =SUM(N75:Y75) | AB75: =IFERROR(IF(UPPER($E75)="L",SUMPRODUCT(N75:Y75,$N$3:$Y$3,$N$2:$Y$2),SUMPRODUCT(N75:Y75,$N$4:$Y$4,$N$2:$Y$2))/(Z75/($K75*$L75*$M75)),"")
A76: 681546 | B76: James Outman | C76: DET | D76: 30 | E76: L | F76: CF | G76: 170 | H76: 1057 | I76: Bench Bat | J76: Opening Day | K76: =IFERROR(INDEX(Roles!$B$17:$B$20,MATCH(J76,Roles!$A$17:$A$20,0)),1) | L76: 1 | M76: 1 | W76: 1 | Z76: =SUMPRODUCT(N76:Y76,$N$2:$Y$2)*$K76*$L76*$M76 | AA76: =SUM(N76:Y76) | AB76: =IFERROR(IF(UPPER($E76)="L",SUMPRODUCT(N76:Y76,$N$3:$Y$3,$N$2:$Y$2),SUMPRODUCT(N76:Y76,$N$4:$Y$4,$N$2:$Y$2))/(Z76/($K76*$L76*$M76)),"")
A77: 701398 | B77: Sal Stewart | C77: CIN | D77: 23 | E77: R | F77: 1B | G77: 700 | H77: 758 | I77: Full Time | J77: Opening Day | K77: =IFERROR(INDEX(Roles!$B$17:$B$20,MATCH(J77,Roles!$A$17:$A$20,0)),1) | L77: 1 | M77: 0.91126714 | N77: 1 | Z77: =SUMPRODUCT(N77:Y77,$N$2:$Y$2)*$K77*$L77*$M77 | AA77: =SUM(N77:Y77) | AB77: =IFERROR(IF(UPPER($E77)="L",SUMPRODUCT(N77:Y77,$N$3:$Y$3,$N$2:$Y$2),SUMPRODUCT(N77:Y77,$N$4:$Y$4,$N$2:$Y$2))/(Z77/($K77*$L77*$M77)),"")
A78: 643217 | B78: Andrew Benintendi | C78: CWS | D78: 32 | E78: L | F78: LF | G78: 468 | H78: 2602 | I78: Everyday DH / 1B-DH | J78: Opening Day | K78: =IFERROR(INDEX(Roles!$B$17:$B$20,MATCH(J78,Roles!$A$17:$A$20,0)),1) | L78: 1 | M78: 1.0093885 | O78: 1 | Z78: =SUMPRODUCT(N78:Y78,$N$2:$Y$2)*$K78*$L78*$M78 | AA78: =SUM(N78:Y78) | AB78: =IFERROR(IF(UPPER($E78)="L",SUMPRODUCT(N78:Y78,$N$3:$Y$3,$N$2:$Y$2),SUMPRODUCT(N78:Y78,$N$4:$Y$4,$N$2:$Y$2))/(Z78/($K78*$L78*$M78)),"")
A79: 642133 | B79: Rowdy Tellez | C79: TEX | D79: 32 | E79: L | F79: 1B | G79: 11 | H79: 1694 | I79: Bench Bat | J79: Opening Day | K79: =IFERROR(INDEX(Roles!$B$17:$B$20,MATCH(J79,Roles!$A$17:$A$20,0)),1) | L79: 1 | M79: 0.79715769 | U79: 0.4 | W79: 0.6 | Z79: =SUMPRODUCT(N79:Y79,$N$2:$Y$2)*$K79*$L79*$M79 | AA79: =SUM(N79:Y79) | AB79: =IFERROR(IF(UPPER($E79)="L",SUMPRODUCT(N79:Y79,$N$3:$Y$3,$N$2:$Y$2),SUMPRODUCT(N79:Y79,$N$4:$Y$4,$N$2:$Y$2))/(Z79/($K79*$L79*$M79)),"")
A80: 669127 | B80: Shea Langeliers | C80: OAK | D80: 29 | E80: R | F80: C | G80: 467 | H80: 2167 | I80: Everyday DH / 1B-DH | J80: Opening Day | K80: =IFERROR(INDEX(Roles!$B$17:$B$20,MATCH(J80,Roles!$A$17:$A$20,0)),1) | L80: 1 | M80: 0.97049137 | O80: 1 | Z80: =SUMPRODUCT(N80:Y80,$N$2:$Y$2)*$K80*$L80*$M80 | AA80: =SUM(N80:Y80) | AB80: =IFERROR(IF(UPPER($E80)="L",SUMPRODUCT(N80:Y80,$N$3:$Y$3,$N$2:$Y$2),SUMPRODUCT(N80:Y80,$N$4:$Y$4,$N$2:$Y$2))/(Z80/($K80*$L80*$M80)),"")
A81: 656555 | B81: Rhys Hoskins | C81: CLE | D81: 34 | E81: R | F81: 1B | G81: 317 | H81: 1834 | I81: Full Time | J81: Opening Day | K81: =IFERROR(INDEX(Roles!$B$17:$B$20,MATCH(J81,Roles!$A$17:$A$20,0)),1) | L81: 1 | M81: 0.85395699 | N81: 1 | Z81: =SUMPRODUCT(N81:Y81,$N$2:$Y$2)*$K81*$L81*$M81 | AA81: =SUM(N81:Y81) | AB81: =IFERROR(IF(UPPER($E81)="L",SUMPRODUCT(N81:Y81,$N$3:$Y$3,$N$2:$Y$2),SUMPRODUCT(N81:Y81,$N$4:$Y$4,$N$2:$Y$2))/(Z81/($K81*$L81*$M81)),"")
A82: 695578 | B82: James Wood | C82: WSH | D82: 24 | E82: L | F82: RF | G82: 623 | H82: 1648 | I82: Everyday DH / 1B-DH | J82: Opening Day | K82: =IFERROR(INDEX(Roles!$B$17:$B$20,MATCH(J82,Roles!$A$17:$A$20,0)),1) | L82: 1 | M82: 1.0694254 | O82: 1 | Z82: =SUMPRODUCT(N82:Y82,$N$2:$Y$2)*$K82*$L82*$M82 | AA82: =SUM(N82:Y82) | AB82: =IFERROR(IF(UPPER($E82)="L",SUMPRODUCT(N82:Y82,$N$3:$Y$3,$N$2:$Y$2),SUMPRODUCT(N82:Y82,$N$4:$Y$4,$N$2:$Y$2))/(Z82/($K82*$L82*$M82)),"")
A83: 660162 | B83: Yoán Moncada | C83: LAA | D83: 32 | E83: S | F83: 3B | G83: 130 | H83: 1254 | I83: Bench Bat | J83: Opening Day | K83: =IFERROR(INDEX(Roles!$B$17:$B$20,MATCH(J83,Roles!$A$17:$A$20,0)),1) | L83: 1 | M83: 1 | W83: 0.7 | X83: 0.3 | Z83: =SUMPRODUCT(N83:Y83,$N$2:$Y$2)*$K83*$L83*$M83 | AA83: =SUM(N83:Y83) | AB83: =IFERROR(IF(UPPER($E83)="L",SUMPRODUCT(N83:Y83,$N$3:$Y$3,$N$2:$Y$2),SUMPRODUCT(N83:Y83,$N$4:$Y$4,$N$2:$Y$2))/(Z83/($K83*$L83*$M83)),"")
A84: 665019 | B84: Kody Clemens | C84: MIN | D84: 31 | E84: L | F84: 2B | G84: 583 | H84: 1364 | I84: Full Time | J84: Opening Day | K84: =IFERROR(INDEX(Roles!$B$17:$B$20,MATCH(J84,Roles!$A$17:$A$20,0)),1) | L84: 1 | M84: 1.0502964 | N84: 0.85 | P84: 0.15 | Z84: =SUMPRODUCT(N84:Y84,$N$2:$Y$2)*$K84*$L84*$M84 | AA84: =SUM(N84:Y84) | AB84: =IFERROR(IF(UPPER($E84)="L",SUMPRODUCT(N84:Y84,$N$3:$Y$3,$N$2:$Y$2),SUMPRODUCT(N84:Y84,$N$4:$Y$4,$N$2:$Y$2))/(Z84/($K84*$L84*$M84)),"")
A85: 669065 | B85: Kyle Stowers | C85: MIA | D85: 29 | E85: L | F85: 1B | G85: 512 | H85: 1309 | I85: Everyday DH / 1B-DH | J85: Opening Day | K85: =IFERROR(INDEX(Roles!$B$17:$B$20,MATCH(J85,Roles!$A$17:$A$20,0)),1) | L85: 1 | M85: 0.99924143 | O85: 1 | Z85: =SUMPRODUCT(N85:Y85,$N$2:$Y$2)*$K85*$L85*$M85 | AA85: =SUM(N85:Y85) | AB85: =IFERROR(IF(UPPER($E85)="L",SUMPRODUCT(N85:Y85,$N$3:$Y$3,$N$2:$Y$2),SUMPRODUCT(N85:Y85,$N$4:$Y$4,$N$2:$Y$2))/(Z85/($K85*$L85*$M85)),"")
A86: 678894 | B86: Liover Peguero | C86: PIT | D86: 26 | E86: R | F86: SS | G86: 88 | H86: 315 | I86: Bench Bat | J86: Opening Day | K86: =IFERROR(INDEX(Roles!$B$17:$B$20,MATCH(J86,Roles!$A$17:$A$20,0)),1) | L86: 1 | M86: 1 | W86: 1 | Z86: =SUMPRODUCT(N86:Y86,$N$2:$Y$2)*$K86*$L86*$M86 | AA86: =SUM(N86:Y86) | AB86: =IFERROR(IF(UPPER($E86)="L",SUMPRODUCT(N86:Y86,$N$3:$Y$3,$N$2:$Y$2),SUMPRODUCT(N86:Y86,$N$4:$Y$4,$N$2:$Y$2))/(Z86/($K86*$L86*$M86)),"")
A87: 657656 | B87: Ramón Laureano | C87: SD | D87: 32 | E87: R | F87: LF | G87: 206 | H87: 1790 | I87: Bench Bat | J87: Opening Day | K87: =IFERROR(INDEX(Roles!$B$17:$B$20,MATCH(J87,Roles!$A$17:$A$20,0)),1) | L87: 1 | M87: 1.0145525 | W87: 0.85 | X87: 0.15 | Z87: =SUMPRODUCT(N87:Y87,$N$2:$Y$2)*$K87*$L87*$M87 | AA87: =SUM(N87:Y87) | AB87: =IFERROR(IF(UPPER($E87)="L",SUMPRODUCT(N87:Y87,$N$3:$Y$3,$N$2:$Y$2),SUMPRODUCT(N87:Y87,$N$4:$Y$4,$N$2:$Y$2))/(Z87/($K87*$L87*$M87)),"")
A88: 596019 | B88: Francisco Lindor | C88: NYM | D88: 33 | E88: S | F88: SS | G88: 469 | H88: 3283 | I88: Full Time | J88: Opening Day | K88: =IFERROR(INDEX(Roles!$B$17:$B$20,MATCH(J88,Roles!$A$17:$A$20,0)),1) | L88: 1 | M88: 1.0443467 | N88: 1 | Z88: =SUMPRODUCT(N88:Y88,$N$2:$Y$2)*$K88*$L88*$M88 | AA88: =SUM(N88:Y88) | AB88: =IFERROR(IF(UPPER($E88)="L",SUMPRODUCT(N88:Y88,$N$3:$Y$3,$N$2:$Y$2),SUMPRODUCT(N88:Y88,$N$4:$Y$4,$N$2:$Y$2))/(Z88/($K88*$L88*$M88)),"")
A89: 687952 | B89: Christian Encarnacion-Strand | C89: BAL | D89: 27 | E89: R | F89: 3B | G89: 213 | H89: 714 | I89: Full Time | J89: Opening Day | K89: =IFERROR(INDEX(Roles!$B$17:$B$20,MATCH(J89,Roles!$A$17:$A$20,0)),1) | L89: 1 | M89: 1 | N89: 0.85 | P89: 0.15 | Z89: =SUMPRODUCT(N89:Y89,$N$2:$Y$2)*$K89*$L89*$M89 | AA89: =SUM(N89:Y89) | AB89: =IFERROR(IF(UPPER($E89)="L",SUMPRODUCT(N89:Y89,$N$3:$Y$3,$N$2:$Y$2),SUMPRODUCT(N89:Y89,$N$4:$Y$4,$N$2:$Y$2))/(Z89/($K89*$L89*$M89)),"")
A90: 608336 | B90: Joey Gallo | C90: WSH | D90: 33 | E90: L | F90: 1B | G90: 260 | H90: 1002 | I90: Depth (no MLB PA) | J90: Opening Day | K90: =IFERROR(INDEX(Roles!$B$17:$B$20,MATCH(J90,Roles!$A$17:$A$20,0)),1) | L90: 1 | M90: 1 | Y90: 1 | Z90: =SUMPRODUCT(N90:Y90,$N$2:$Y$2)*$K90*$L90*$M90 | AA90: =SUM(N90:Y90) | AB90: =IFERROR(IF(UPPER($E90)="L",SUMPRODUCT(N90:Y90,$N$3:$Y$3,$N$2:$Y$2),SUMPRODUCT(N90:Y90,$N$4:$Y$4,$N$2:$Y$2))/(Z90/($K90*$L90*$M90)),"")
A91: 682987 | B91: Spencer Jones | C91: NYY | D91: 26 | E91: L | F91: CF | G91: 289 | H91: 289 | I91: Full Time | J91: Opening Day | K91: =IFERROR(INDEX(Roles!$B$17:$B$20,MATCH(J91,Roles!$A$17:$A$20,0)),1) | L91: 1 | M91: 1 | N91: 0.7 | P91: 0.3 | Z91: =SUMPRODUCT(N91:Y91,$N$2:$Y$2)*$K91*$L91*$M91 | AA91: =SUM(N91:Y91) | AB91: =IFERROR(IF(UPPER($E91)="L",SUMPRODUCT(N91:Y91,$N$3:$Y$3,$N$2:$Y$2),SUMPRODUCT(N91:Y91,$N$4:$Y$4,$N$2:$Y$2))/(Z91/($K91*$L91*$M91)),"")
A92: 815873 | B92: Sean Keys | C92: TOR | D92: 24 | E92: L | F92: 1B | G92: 67 | H92: 67 | I92: Bench Bat | J92: Opening Day | K92: =IFERROR(INDEX(Roles!$B$17:$B$20,MATCH(J92,Roles!$A$17:$A$20,0)),1) | L92: 1 | M92: 1 | U92: 0.4 | W92: 0.6 | Z92: =SUMPRODUCT(N92:Y92,$N$2:$Y$2)*$K92*$L92*$M92 | AA92: =SUM(N92:Y92) | AB92: =IFERROR(IF(UPPER($E92)="L",SUMPRODUCT(N92:Y92,$N$3:$Y$3,$N$2:$Y$2),SUMPRODUCT(N92:Y92,$N$4:$Y$4,$N$2:$Y$2))/(Z92/($K92*$L92*$M92)),"")
A93: 682674 | B93: Victor Bericoto | C93: SF | D93: 25 | E93: R | F93: LF | G93: 116 | H93: 116 | I93: Weak Side Platoon | J93: Opening Day | K93: =IFERROR(INDEX(Roles!$B$17:$B$20,MATCH(J93,Roles!$A$17:$A$20,0)),1) | L93: 1 | M93: 1 | Q93: 0.6 | U93: 0.4 | Z93: =SUMPRODUCT(N93:Y93,$N$2:$Y$2)*$K93*$L93*$M93 | AA93: =SUM(N93:Y93) | AB93: =IFERROR(IF(UPPER($E93)="L",SUMPRODUCT(N93:Y93,$N$3:$Y$3,$N$2:$Y$2),SUMPRODUCT(N93:Y93,$N$4:$Y$4,$N$2:$Y$2))/(Z93/($K93*$L93*$M93)),"")
A94: 650907 | B94: René Pinto | C94: TB | D94: 30 | E94: R | F94: C | G94: 49 | H94: 237 | I94: Depth (no MLB PA) | J94: Opening Day | K94: =IFERROR(INDEX(Roles!$B$17:$B$20,MATCH(J94,Roles!$A$17:$A$20,0)),1) | L94: 1 | M94: 1 | Y94: 1 | Z94: =SUMPRODUCT(N94:Y94,$N$2:$Y$2)*$K94*$L94*$M94 | AA94: =SUM(N94:Y94) | AB94: =IFERROR(IF(UPPER($E94)="L",SUMPRODUCT(N94:Y94,$N$3:$Y$3,$N$2:$Y$2),SUMPRODUCT(N94:Y94,$N$4:$Y$4,$N$2:$Y$2))/(Z94/($K94*$L94*$M94)),"")
A95: 700932 | B95: Kyle Manzardo | C95: CLE | D95: 26 | E95: L | F95: 1B | G95: 356 | H95: 1043 | I95: Everyday DH / 1B-DH | J95: Opening Day | K95: =IFERROR(INDEX(Roles!$B$17:$B$20,MATCH(J95,Roles!$A$17:$A$20,0)),1) | L95: 1 | M95: 0.89777065 | O95: 1 | Z95: =SUMPRODUCT(N95:Y95,$N$2:$Y$2)*$K95*$L95*$M95 | AA95: =SUM(N95:Y95) | AB95: =IFERROR(IF(UPPER($E95)="L",SUMPRODUCT(N95:Y95,$N$3:$Y$3,$N$2:$Y$2),SUMPRODUCT(N95:Y95,$N$4:$Y$4,$N$2:$Y$2))/(Z95/($K95*$L95*$M95)),"")
A96: 676914 | B96: Davis Schneider | C96: TOR | D96: 28 | E96: R | F96: LF | G96: 156 | H96: 978 | I96: Bench Bat | J96: Opening Day | K96: =IFERROR(INDEX(Roles!$B$17:$B$20,MATCH(J96,Roles!$A$17:$A$20,0)),1) | L96: 1 | M96: 0.97798142 | U96: 0.4 | W96: 0.6 | Z96: =SUMPRODUCT(N96:Y96,$N$2:$Y$2)*$K96*$L96*$M96 | AA96: =SUM(N96:Y96) | AB96: =IFERROR(IF(UPPER($E96)="L",SUMPRODUCT(N96:Y96,$N$3:$Y$3,$N$2:$Y$2),SUMPRODUCT(N96:Y96,$N$4:$Y$4,$N$2:$Y$2))/(Z96/($K96*$L96*$M96)),"")
A97: 691181 | B97: Emmanuel Rodriguez | C97: MIN | D97: 24 | E97: L | F97: LF | G97: 48 | H97: 48 | I97: Full Time | J97: Opening Day | K97: =IFERROR(INDEX(Roles!$B$17:$B$20,MATCH(J97,Roles!$A$17:$A$20,0)),1) | L97: 1 | M97: 1 | N97: 0.62 | P97: 0.38 | Z97: =SUMPRODUCT(N97:Y97,$N$2:$Y$2)*$K97*$L97*$M97 | AA97: =SUM(N97:Y97) | AB97: =IFERROR(IF(UPPER($E97)="L",SUMPRODUCT(N97:Y97,$N$3:$Y$3,$N$2:$Y$2),SUMPRODUCT(N97:Y97,$N$4:$Y$4,$N$2:$Y$2))/(Z97/($K97*$L97*$M97)),"")
A98: 665862 | B98: Jazz Chisholm Jr. | C98: NYY | D98: 29 | E98: L | F98: 2B | G98: 532 | H98: 2308 | I98: Full Time | J98: Opening Day | K98: =IFERROR(INDEX(Roles!$B$17:$B$20,MATCH(J98,Roles!$A$17:$A$20,0)),1) | L98: 1 | M98: 1.0732452 | N98: 0.7 | P98: 0.3 | Z98: =SUMPRODUCT(N98:Y98,$N$2:$Y$2)*$K98*$L98*$M98 | AA98: =SUM(N98:Y98) | AB98: =IFERROR(IF(UPPER($E98)="L",SUMPRODUCT(N98:Y98,$N$3:$Y$3,$N$2:$Y$2),SUMPRODUCT(N98:Y98,$N$4:$Y$4,$N$2:$Y$2))/(Z98/($K98*$L98*$M98)),"")
A99: 462101 | B99: Elvis Andrus | C99: CWS | D99: 38 | E99: R | F99: 2B | G99: 406 | H99: 983 | I99: Depth (no MLB PA) | J99: Opening Day | K99: =IFERROR(INDEX(Roles!$B$17:$B$20,MATCH(J99,Roles!$A$17:$A$20,0)),1) | L99: 1 | M99: 1 | Y99: 1 | Z99: =SUMPRODUCT(N99:Y99,$N$2:$Y$2)*$K99*$L99*$M99 | AA99: =SUM(N99:Y99) | AB99: =IFERROR(IF(UPPER($E99)="L",SUMPRODUCT(N99:Y99,$N$3:$Y$3,$N$2:$Y$2),SUMPRODUCT(N99:Y99,$N$4:$Y$4,$N$2:$Y$2))/(Z99/($K99*$L99*$M99)),"")
A100: 668901 | B100: Mark Vientos | C100: NYM | D100: 27 | E100: R | F100: 1B | G100: 295 | H100: 1486 | I100: Everyday DH / 1B-DH | J100: Opening Day | K100: =IFERROR(INDEX(Roles!$B$17:$B$20,MATCH(J100,Roles!$A$17:$A$20,0)),1) | L100: 1 | M100: 0.88339562 | O100: 0.7 | W100: 0.3 | Z100: =SUMPRODUCT(N100:Y100,$N$2:$Y$2)*$K100*$L100*$M100 | AA100: =SUM(N100:Y100) | AB100: =IFERROR(IF(UPPER($E100)="L",SUMPRODUCT(N100:Y100,$N$3:$Y$3,$N$2:$Y$2),SUMPRODUCT(N100:Y100,$N$4:$Y$4,$N$2:$Y$2))/(Z100/($K100*$L100*$M100)),"")
...

Sheet Roles
A1: Role | B1: PA Anchor | C1: vL Share (LHB) | D1: vL Share (RHB) | E1: Definition / notes
A2: Full Time | B2: 630 | C2: 0.26 | D2: 0.29 | E2: Everyday regular, ~150 games. Sees the league handedness mix.
A3: Everyday DH / 1B-DH | B3: 600 | C3: 0.26 | D3: 0.29 | E3: Rarely rested, no defensive injury exposure.
A4: Strong Side Platoon | B4: 480 | C4: 0.12 | D4: 0.45 | E4: The high-volume half of a platoon — usually a LHB who sits against LHP. Plays the majority of games.
A5: Weak Side Platoon | B5: 230 | C5: 0.08 | D5: 0.68 | E5: The low-volume half — usually a RHB who plays mostly against LHP. Only ~28% of league PA are vs LHP, which caps his volume.
A6: Catcher - Primary | B6: 500 | C6: 0.26 | D6: 0.29 | E6: CATCHERS HAVE THEIR OWN LADDER. A full-time catcher is ~500 PA, not 630 — applying the Full Time anchor over-projects every catcher in baseball by ~120 PA.
A7: Catcher - Tandem | B7: 340 | C7: 0.22 | D7: 0.38 | E7: Roughly even split with a partner; often matchup-managed.
A8: Catcher - Backup | B8: 180 | C8: 0.24 | D8: 0.33 | E8: Clear #2, starts ~45-55 games.
A9: Utility IF | B9: 290 | C9: 0.26 | D9: 0.31 | E9: Covers multiple infield spots; volume depends on incumbents' health.
A10: Utility OF / 4th OF | B10: 300 | C10: 0.24 | D10: 0.33 | E10: Distinct from Utility IF — different volume and platoon usage.
A11: Bench Bat | B11: 150 | C11: 0.22 | D11: 0.36 | E11: Pinch-hits and spot starts.
A12: Injury Replacement / 26th Man | B12: 90 | C12: 0.26 | D12: 0.29 | E12: Plays only when someone ahead of him is hurt. His volume is conditional on OTHER players' injuries — a team-level coupling that ultimately needs simulating, not a point estimate.
A13: Depth (no MLB PA) | B13: 1 | C13: 0.26 | D13: 0.29 | E13: Organizational depth. Hits the 1 PA floor (PT_FLOOR_PA) so he stays present and joinable without moving any aggregate.
A15: Role Start -> Role Share
A16: Role Start | B16: Role Share | C16: Meaning
A17: Opening Day | B17: 1 | C17: On the roster from day one.
A18: Early Season (~May) | B18: 0.8 | C18: Called up or activated in April/May.
A19: Mid Season (~July) | B19: 0.5 | C19: Mid-season callup, or back from a long IL stay.
A20: Late Season (~Sept) | B20: 0.2 | C20: September callup / late activation.
A22: Anchors are per 162 team games at full availability with the role held all season. Multiply by Role Share and Availability.

Sheet Teams
A1: Team | B1: pa_share | C1: Expected signing / note
A2: ARI | B2: 0
A3: ATL | B3: 0
A4: BAL | B4: 0
A5: BOS | B5: 0
A6: CHC | B6: 0
A7: CIN | B7: 0
A8: CLE | B8: 0
A9: COL | B9: 0
A10: CWS | B10: 0
A11: DET | B11: 0
A12: HOU | B12: 0
A13: KC | B13: 0
... A31: WSH | B31: 0
A33: Fraction of each club's PA budget held back for a signing it has not made yet. 0 to 0.5.
A34: Without a reserve the allocator spreads the full budget across the players currently on hand, so every incumbent absorbs the playing time that will actually go to the free agent.
A35: A reserve says 'this club's playing time is not all accounted for'. It does NOT say the club is better than its roster looks — the quality of an unsigned player is unknowable, so reserves never touch the rate projections.
A36: Copy these into the "reserves" block of rosters/team_assignments_<year>.json, which is what the pipeline reads.
